{
  "hobbys": {
    "hobby": [
      {
        "name": "映画・ドラマ鑑賞",
        "status": {
          "sociability": -1,
          "collect": 0,
          "multiPlay": -2,
          "selfPolishing": 1,
          "art": 1,
          "sport": -2,
          "it": 1,
          "margin": 1,
          "costPerformance": 2,
          "text": "■インドア派の鉄板<br>話題に困らないかも！？<br>SF・恋愛・刑事、色々な世界を疑似体験しよう！！"
        }
      },
      {
        "name": "スポーツ観戦",
        "status": {
          "sociability": 2,
          "collect": -2,
          "multiPlay": 1,
          "selfPolishing": -2,
          "art": -2,
          "sport": 2,
          "it": 0,
          "margin": 1,
          "costPerformance": -1,
          "text": "■インドア派の鉄板<br>甲子園からWBC、W杯までスポーツの数だけ趣味の幅が広がる！"
        }
      },
      {
        "name": "梅酒作り",
        "status": {
          "sociability": -2,
          "collect": 1,
          "multiPlay": -2,
          "selfPolishing": 1,
          "art": -2,
          "sport": -2,
          "it": -2,
          "margin": -2,
          "costPerformance": 2,
          "text": "■美味しい物作り<br>意外と簡単につくれる！？<br>自分好みの梅酒を楽しもう！"
        }
      },
      {
        "name": "マッサージ",
        "status": {
          "sociability": 1,
          "collect": -2,
          "multiPlay": -2,
          "selfPolishing": 1,
          "art": 1,
          "sport": -2,
          "it": -2,
          "margin": 1,
          "costPerformance": -1,
          "text": "■疲れた時の癒し<br>マッサージ・エステ・サロンで心身ともに癒されよう<br>グッズを買って自宅で癒されるの良いかも！？"
        }
      },
      {
        "name": "日記",
        "status": {
          "sociability": -2,
          "collect": 2,
          "multiPlay": -2,
          "selfPolishing": 1,
          "art": 1,
          "sport": -2,
          "it": -2,
          "margin": -2,
          "costPerformance": 2,
          "text": "■思い出作り<br>日々の思いを綴ろう！<br>より生産的な毎日が遅れる効果も！？"
        }
      },
      {
        "name": "絵日記",
        "status": {
          "sociability": -2,
          "collect": 2,
          "multiPlay": -2,
          "selfPolishing": 1,
          "art": 2,
          "sport": -2,
          "it": -2,
          "margin": -2,
          "costPerformance": 2,
          "text": "■思い出作り<br>日々の思いを綴ろう<br>イラストを書き続けて絵も上手くなるかも！？"
        }
      },
      {
        "name": "飲酒",
        "status": {
          "sociability": 2,
          "collect": 1,
          "multiPlay": 1,
          "selfPolishing": -1,
          "art": -2,
          "sport": -2,
          "it": -2,
          "margin": 1,
          "costPerformance": -2,
          "text": "■大人の癒し<br>一人でしっぽり飲むも良し！みんなでワイワイ飲むも良し！<br>カクテル・ワイン・焼酎・日本酒・ウイスキー何が好き？"
        }
      },
      {
        "name": "囲碁・将棋・オセロ・チェス",
        "status": {
          "sociability": 1,
          "collect": 0,
          "multiPlay": -2,
          "selfPolishing": 2,
          "art": 1,
          "sport": 1,
          "it": 1,
          "margin": 1,
          "costPerformance": 2,
          "text": "■頭脳スポーツ<br>論理的思考能力を高めよう！<br>アマチュアでも定石を作った実績も！！"
        }
      },
      {
        "name": "英会話",
        "status": {
          "sociability": 2,
          "collect": -2,
          "multiPlay": 2,
          "selfPolishing": 2,
          "art": -2,
          "sport": -2,
          "it": 1,
          "margin": 2,
          "costPerformance": -1,
          "text": "■キャリアアップ<br>英語を習得するいいチャンス！<br>外国人と友達・恋人になる夢が叶うかも！？"
        }
      },
      {
        "name": "折り紙",
        "status": {
          "sociability": -2,
          "collect": 2,
          "multiPlay": -2,
          "selfPolishing": -2,
          "art": 2,
          "sport": -2,
          "it": -2,
          "margin": -2,
          "costPerformance": 2,
          "text": "■意外性抜群<br>手軽に始められるのに意外と奥深い<br>郵便に挟むのもオシャレ！"
        }
      },
      {
        "name": "占い",
        "status": {
          "sociability": 2,
          "collect": 2,
          "multiPlay": 1,
          "selfPolishing": 2,
          "art": 1,
          "sport": -2,
          "it": -2,
          "margin": 1,
          "costPerformance": 2,
          "text": "■趣味から職業に<br>占いでラッキーな毎日を！<br>いつのまにか占い師になれるかも！？"
        }
      },
      {
        "name": "アロマ",
        "status": {
          "sociability": -2,
          "collect": 2,
          "multiPlay": -2,
          "selfPolishing": 1,
          "art": 2,
          "sport": -2,
          "it": -2,
          "margin": -2,
          "costPerformance": -1,
          "text": "■オシャレな癒し<br>リラックス効果抜群！<br>異性からモテモテになれるかも！？"
        }
      },
      {
        "name": "裁縫・編み物",
        "status": {
          "sociability": 1,
          "collect": 2,
          "multiPlay": -2,
          "selfPolishing": 2,
          "art": 2,
          "sport": -2,
          "it": -2,
          "margin": 1,
          "costPerformance": -1,
          "text": "■意外性抜群<bとても家庭的。<br>日常で着る洋服からぬいぐるみまで、自分で作れる！"
        }
      },
      {
        "name": "ブログ",
        "status": {
          "sociability": 2,
          "collect": 2,
          "multiPlay": -2,
          "selfPolishing": 1,
          "art": 1,
          "sport": -2,
          "it": 2,
          "margin": -1,
          "costPerformance": 2,
          "text": "■思い出作り<br>日々の思いを綴ろう<br>広告を出すことで収入を得ることも！"
        }
      },
      {
        "name": "フラワーアレンジメント",
        "status": {
          "sociability": 1,
          "collect": 2,
          "multiPlay": -2,
          "selfPolishing": 1,
          "art": 2,
          "sport": -2,
          "it": -2,
          "margin": 2,
          "costPerformance": -1,
          "text": "■癒し<br>水やりが必要ない！？自由な発想で楽しめる<br>心を穏やかにし、リラックスしよう"
        }
      },
      {
        "name": "宝くじ",
        "status": {
          "sociability": 1,
          "collect": 2,
          "multiPlay": -2,
          "selfPolishing": -2,
          "art": -2,
          "sport": -2,
          "it": -2,
          "margin": -2,
          "costPerformance": -1,
          "text": "■一攫千金<br>お金持ちになって色々な夢を叶えよう<br>意外と規則性があるかも！？"
        }
      },
      {
        "name": "ベース・ギター・ドラム",
        "status": {
          "sociability": 2,
          "collect": 1,
          "multiPlay": 1,
          "selfPolishing": 2,
          "art": 2,
          "sport": -2,
          "it": -2,
          "margin": 2,
          "costPerformance": -2,
          "text": "■センスが光る<br>感性を磨こう<br>自分で弾けるようになったらモテモテかも！？"
        }
      },
      {
        "name": "ペット飼育",
        "status": {
          "sociability": 2,
          "collect": -1,
          "multiPlay": -2,
          "selfPolishing": -2,
          "art": -2,
          "sport": -2,
          "it": -2,
          "margin": 2,
          "costPerformance": -2,
          "text": "■話題性抜群の癒し<br>犬や猫だけじゃない！<br>フェレット、ハリネズミなど一風変わったペットで癒されよう"
        }
      },
      {
        "name": "プラモデル",
        "status": {
          "sociability": -2,
          "collect": 2,
          "multiPlay": -2,
          "selfPolishing": -2,
          "art": 1,
          "sport": -2,
          "it": 1,
          "margin": 1,
          "costPerformance": -1,
          "text": "■インドア派の鉄板<br>精密に作り上げるだけでなくカスタマイズできるのも魅力！<br>器用さを磨こう"
        }
      },
      {
        "name": "ペーパークラフト",
        "status": {
          "sociability": -2,
          "collect": 2,
          "multiPlay": -2,
          "selfPolishing": -2,
          "art": 2,
          "sport": -2,
          "it": -2,
          "margin": -1,
          "costPerformance": 2,
          "text": "■意外性抜群<br>自分だけの世界を作ることができる！？<br>手軽に始められるのが魅力！"
        }
      },
      {
        "name": "ミニカー",
        "status": {
          "sociability": -2,
          "collect": 2,
          "multiPlay": -2,
          "selfPolishing": -2,
          "art": 2,
          "sport": -2,
          "it": -2,
          "margin": -2,
          "costPerformance": -1,
          "text": "■コレクション<br>実物さながらの精密さに驚愕！？<br>どんな高級車でもあなたのもの！"
        }
      },
      {
        "name": "ポエム・俳句",
        "status": {
          "sociability": 1,
          "collect": 2,
          "multiPlay": -1,
          "selfPolishing": 2,
          "art": 2,
          "sport": -2,
          "it": -2,
          "margin": -2,
          "costPerformance": 2,
          "text": "■感性を磨く<br>あなたの思いを凝縮しよう<br>魅力的な語彙力がつくかも！？"
        }
      },
      {
        "name": "ボーカロイド",
        "status": {
          "sociability": -2,
          "collect": -2,
          "multiPlay": -2,
          "selfPolishing": 1,
          "art": 2,
          "sport": -2,
          "it": 2,
          "margin": 2,
          "costPerformance": 2,
          "text": "■意外性抜群<br>未完成なのが魅力！？<br>どんなジャンルの音楽でも聴けるのもまた魅力！"
        }
      },
      {
        "name": "葉巻・タバコ",
        "status": {
          "sociability": 2,
          "collect": 2,
          "multiPlay": 1,
          "selfPolishing": -2,
          "art": -2,
          "sport": -2,
          "it": -2,
          "margin": -2,
          "costPerformance": -2,
          "text": "■大人の癒し<br>ブランドごと、生産年、保存状態などで味が変わり、その香りで心が満ちる<br>よりかっこよさを極めよう"
        }
      },
      {
        "name": "絵画",
        "status": {
          "sociability": 2,
          "collect": 2,
          "multiPlay": -1,
          "selfPolishing": -2,
          "art": 2,
          "sport": -2,
          "it": -2,
          "margin": 2,
          "costPerformance": -1,
          "text": "■感性を磨く<br>正解なんてない！あなたが好きな作品があなたにとっての最高傑作<br>誰でも絵師になれる！？"
        }
      },
      {
        "name": "電子工作・パソコン自作",
        "status": {
          "sociability": -2,
          "collect": 2,
          "multiPlay": -2,
          "selfPolishing": 2,
          "art": -2,
          "sport": -2,
          "it": -2,
          "margin": 2,
          "costPerformance": -2,
          "text": "■じっくり物作り<br>あなたならではの物を作ろう！<br>オシャレなランプなどなんでもつくれる！？"
        }
      },
      {
        "name": "コスプレ・男装・女装",
        "status": {
          "sociability": -1,
          "collect": 2,
          "multiPlay": -1,
          "selfPolishing": 0,
          "art": 1,
          "sport": -2,
          "it": -2,
          "margin": 2,
          "costPerformance": -2,
          "text": "■意外性抜群<br>なりたい姿になろう！<br>別人になって別世界を満喫しよう"
        }
      },
      {
        "name": "百人一首",
        "status": {
          "sociability": -1,
          "collect": 2,
          "multiPlay": 0,
          "selfPolishing": -2,
          "art": -1,
          "sport": -2,
          "it": -2,
          "margin": -2,
          "costPerformance": 2,
          "text": "■感性を磨く<br>千年も前に生きていた人たちが、今の自分と同じ感性を持っている！？<br>季節を表すたくさんの繊細な色の名前や、大和言葉と呼ばれる奥ゆかしくもすっきりした言葉に触れよう"
        }
      },
      {
        "name": "麻雀",
        "status": {
          "sociability": 2,
          "collect": 1,
          "multiPlay": 2,
          "selfPolishing": -1,
          "art": -2,
          "sport": 1,
          "it": -2,
          "margin": 2,
          "costPerformance": -1,
          "text": "■頭脳スポーツ<br>唯一アマチュアがプロに勝てるゲーム！？<br>賭け麻雀は厳禁！"
        }
      },
      {
        "name": "妄想・瞑想",
        "status": {
          "sociability": -2,
          "collect": -2,
          "multiPlay": 2,
          "selfPolishing": 2,
          "art": 2,
          "sport": -2,
          "it": -2,
          "margin": -2,
          "costPerformance": 2,
          "text": "■感性を磨く<br>想像力・集中力を育もう！<br>心身ともに健康になる！？"
        }
      },
      {
        "name": "掃除",
        "status": {
          "sociability": -2,
          "collect": 0,
          "multiPlay": -2,
          "selfPolishing": 1,
          "art": -2,
          "sport": -2,
          "it": -2,
          "margin": 1,
          "costPerformance": 1,
          "text": "■<br>物を片付けることでスペースが広くなり、暮らしの動線がスムーズになって効率が良くなる！？<br>環境を整えて心を落ち着かせよう"
        }
      },
      {
        "name": "手紙",
        "status": {
          "sociability": 1,
          "collect": 2,
          "multiPlay": 2,
          "selfPolishing": 1,
          "art": 2,
          "sport": -2,
          "it": -2,
          "margin": 0,
          "costPerformance": 1,
          "text": "■意外性抜群<br>直筆だからこそ嬉しい！より思いを伝えよう<br>段々と字が綺麗になっていくかも！？"
        }
      },
      {
        "name": "歴史",
        "status": {
          "sociability": -1,
          "collect": 2,
          "multiPlay": -2,
          "selfPolishing": 2,
          "art": -2,
          "sport": -2,
          "it": -2,
          "margin": 2,
          "costPerformance": 2,
          "text": "■意外性抜群<br>時間と人が織りなす物語が魅力<br>色々なもののルーツを探るのも良いかも"
        }
      },
      {
        "name": "木工・大工・DIY",
        "status": {
          "sociability": 2,
          "collect": 2,
          "multiPlay": -2,
          "selfPolishing": 1,
          "art": 2,
          "sport": -2,
          "it": -2,
          "margin": 2,
          "costPerformance": -2,
          "text": "■流行<br>意外と手軽に始められる！？<br>自分だけのリラックス空間を作り上げよう"
        }
      },
      {
        "name": "youtube鑑賞",
        "status": {
          "sociability": -2,
          "collect": -2,
          "multiPlay": -2,
          "selfPolishing": -1,
          "art": -2,
          "sport": -2,
          "it": 1,
          "margin": 1,
          "costPerformance": 2,
          "text": "■とても楽々<br>料理・サバイバル・音楽・アニメ・イタヅラ、コンテンツの種類・量は一番！<br>毎日、様々な刺激を受けよう！"
        }
      },
      {
        "name": "動画・生放送配信(youtuber)",
        "status": {
          "sociability": 1,
          "collect": -2,
          "multiPlay": -2,
          "selfPolishing": 1,
          "art": 1,
          "sport": -2,
          "it": 1,
          "margin": 2,
          "costPerformance": 2,
          "text": "■流行<br>今からでも遅くない！？趣味で少しづつ稼ごう<br>好きな内容で好きなように配信しよう！"
        }
      },
      {
        "name": "筋トレ・ボディビルディング",
        "status": {
          "sociability": 2,
          "collect": 1,
          "multiPlay": -2,
          "selfPolishing": 2,
          "art": -2,
          "sport": 2,
          "it": -2,
          "margin": -1,
          "costPerformance": 1,
          "text": "■自己研磨<br>運動しやすいだけじゃなく、結果が目に見えて自身がつくのが魅力！<br>モテモテ間違いなし！？"
        }
      },
      {
        "name": "パン作り",
        "status": {
          "sociability": 1,
          "collect": 2,
          "multiPlay": -2,
          "selfPolishing": 1,
          "art": 1,
          "sport": -2,
          "it": -2,
          "margin": 2,
          "costPerformance": -1,
          "text": "■美味しいものづくり<br>焼きたてパンがいくらでも食べられる！<br>自分好みをパンを作り上げよう！！"
        }
      },
      {
        "name": "ピアノ",
        "status": {
          "sociability": 1,
          "collect": -2,
          "multiPlay": -2,
          "selfPolishing": 2,
          "art": 2,
          "sport": -2,
          "it": -2,
          "margin": -2,
          "costPerformance": -2,
          "text": "■センスが光る<br>鍵盤を押すだけで、たちまち気持ちのいいピアノの音がはね返ってくる！<br>メロディー、ハーモニー、リズムという音楽の3要素を丸々楽しもう！！"
        }
      },
      {
        "name": "レゴ",
        "status": {
          "sociability": -2,
          "collect": 2,
          "multiPlay": -2,
          "selfPolishing": 1,
          "art": 2,
          "sport": -2,
          "it": -2,
          "margin": -1,
          "costPerformance": 2,
          "text": "■センスが光るものづくり<br>コンテストでの入賞もできるかも！？<br>自分の発想を生かせる、自由度の高さがピカイチ！映画のワンシーンの再現も！？"
        }
      },
      {
        "name": "手品",
        "status": {
          "sociability": 2,
          "collect": 2,
          "multiPlay": -2,
          "selfPolishing": 2,
          "art": 2,
          "sport": -2,
          "it": -2,
          "margin": 1,
          "costPerformance": -1,
          "text": "■意外性抜群<br>人をあっと言わせよう！<br>手品独特の超能力の世界観に浸ろう！！"
        }
      },
      {
        "name": "ファッション",
        "status": {
          "sociability": 2,
          "collect": 2,
          "multiPlay": -2,
          "selfPolishing": 2,
          "art": 2,
          "sport": -2,
          "it": -2,
          "margin": 1,
          "costPerformance": -2,
          "text": "■センスが光る<br>性別もなく自分次第で何でもできる！？<br>ブランドにこだわるのもあり！"
        }
      },
      {
        "name": "ネイルアート",
        "status": {
          "sociability": 1,
          "collect": 2,
          "multiPlay": -2,
          "selfPolishing": 2,
          "art": 2,
          "sport": -2,
          "it": -2,
          "margin": 1,
          "costPerformance": -1,
          "text": "■自己研磨<br>爪や指先をケアしていると無意識に手に対する注意力が高まり、些細な動きや振る舞いでも一つ一つの動作が丁寧になる！？<br>独創性やクオリティの高さには驚くはず"
        }
      },
      {
        "name": "掲示板",
        "status": {
          "sociability": 1,
          "collect": -2,
          "multiPlay": 1,
          "selfPolishing": 1,
          "art": -2,
          "sport": -2,
          "it": 1,
          "margin": -2,
          "costPerformance": 2,
          "text": "■意外性抜群<br>匿名で好きに好きなことを言えるのが魅力<br>気づいたら癖になってるかも！？"
        }
      },
      {
        "name": "プログラミング",
        "status": {
          "sociability": 2,
          "collect": -2,
          "multiPlay": -2,
          "selfPolishing": 2,
          "art": 1,
          "sport": -2,
          "it": 2,
          "margin": 2,
          "costPerformance": 1,
          "text": "■自己研磨<br>論理的思考能力を高めよう！<br>自由自在にものづくりできる！一攫千金のチャンスも！？"
        }
      },
      {
        "name": "テレビ・ラジオ鑑賞",
        "status": {
          "sociability": 1,
          "collect": -2,
          "multiPlay": -2,
          "selfPolishing": -1,
          "art": -2,
          "sport": -2,
          "it": -2,
          "margin": 2,
          "costPerformance": 2,
          "text": "■インドア派の鉄板<br>ながら作業にはもってこい！<br>ニュースなど様々な情報入手ができる！！"
        }
      },
      {
        "name": "デコアート",
        "status": {
          "sociability": 1,
          "collect": 1,
          "multiPlay": -2,
          "selfPolishing": 1,
          "art": 1,
          "sport": -2,
          "it": -2,
          "margin": 1,
          "costPerformance": 1,
          "text": "■センスが光る<br>きらきら光るラインストーンが魅力<br>日本デコアーティスト協会が監修している講座もある！？"
        }
      },
      {
        "name": "マナー習得",
        "status": {
          "sociability": 2,
          "collect": -2,
          "multiPlay": -2,
          "selfPolishing": 2,
          "art": -2,
          "sport": -2,
          "it": -2,
          "margin": 1,
          "costPerformance": -1,
          "text": "■自己研磨<br>好印象を与えて仕事も恋愛も円滑に！？<br>気品溢れる大人にろう！"
        }
      },
      {
        "name": "盆栽・ガーデニング",
        "status": {
          "sociability": 1,
          "collect": 2,
          "multiPlay": -2,
          "selfPolishing": -2,
          "art": -2,
          "sport": -2,
          "it": -2,
          "margin": -1,
          "costPerformance": -1,
          "text": "■感性を磨く<br>「自然美」と「人工美」の調和が魅力<br>適度に日光を浴びて、美しい庭に癒されよう"
        }
      },
      {
        "name": "陶芸",
        "status": {
          "sociability": 1,
          "collect": -2,
          "multiPlay": -2,
          "selfPolishing": 1,
          "art": 2,
          "sport": -2,
          "it": -2,
          "margin": 2,
          "costPerformance": -1,
          "text": "■じっくりものづくり<br>自分に合う、自分だけの器を作ろう<br>自分の手で創造する楽しさにやみつきに！？"
        }
      },
      {
        "name": "落語",
        "status": {
          "sociability": 1,
          "collect": -2,
          "multiPlay": -2,
          "selfPolishing": 2,
          "art": 2,
          "sport": -2,
          "it": -2,
          "margin": 1,
          "costPerformance": -1,
          "text": "■感性を磨く<br>笑いの元祖！<br>語彙力・表現力がいつのまにか自分のものに！？"
        }
      },
      {
        "name": "漬物・味噌",
        "status": {
          "sociability": -2,
          "collect": 2,
          "multiPlay": -2,
          "selfPolishing": -2,
          "art": -2,
          "sport": -2,
          "it": -2,
          "margin": -2,
          "costPerformance": 2,
          "text": "■美味しいものづくり<br>栄養が詰まった皮もまるごと食べれるので無駄がない！<br>長期保存が可能でいつでも食べられる！！"
        }
      },
      {
        "name": "音楽鑑賞",
        "status": {
          "sociability": 2,
          "collect": 2,
          "multiPlay": -2,
          "selfPolishing": -1,
          "art": 2,
          "sport": -2,
          "it": -2,
          "margin": -2,
          "costPerformance": 2,
          "text": "■感性を磨く<br>pcやスマホがあれば手軽に始められる<br>様々なジャンルの音楽を聴きまくろう！！"
        }
      },
      {
        "name": "天体観測",
        "status": {
          "sociability": -2,
          "collect": 1,
          "multiPlay": -2,
          "selfPolishing": -1,
          "art": 2,
          "sport": -2,
          "it": 0,
          "margin": 2,
          "costPerformance": -2,
          "text": "■大人の癒し<br>ゆったりロマン溢れる時間をすごそう！<br>彗星、新星等を最初に見つけちゃうかも！？"
        }
      },
      {
        "name": "TRPG",
        "status": {
          "sociability": 2,
          "collect": -2,
          "multiPlay": 2,
          "selfPolishing": 1,
          "art": 2,
          "sport": 1,
          "it": -2,
          "margin": 2,
          "costPerformance": 2,
          "text": "■想像力向上<br>いつのまにか想像力・演技力が身についているかも！？<br>自分のデザインした物語で遊ぼう！"
        }
      },
      {
        "name": "書道・茶道・華道・着付け",
        "status": {
          "sociability": 2,
          "collect": 1,
          "multiPlay": -2,
          "selfPolishing": 2,
          "art": 2,
          "sport": -2,
          "it": -2,
          "margin": 1,
          "costPerformance": -1,
          "text": "■自己研磨<br>気品溢れる大人になろう！<br道を極めて心も豊かに！？>"
        }
      },
      {
        "name": "手話",
        "status": {
          "sociability": 2,
          "collect": 1,
          "multiPlay": -2,
          "selfPolishing": 2,
          "art": 2,
          "sport": -2,
          "it": -2,
          "margin": 1,
          "costPerformance": -1,
          "text": "■自己研磨<br>語源を知るとその魅力に囚われる！？<br>身体を使った表現を！"
        }
      },
      {
        "name": "自己啓発",
        "status": {
          "sociability": 2,
          "collect": 1,
          "multiPlay": -2,
          "selfPolishing": 2,
          "art": -2,
          "sport": -2,
          "it": -2,
          "margin": 1,
          "costPerformance": -1,
          "text": "■自己研磨<br>自分自身の魅力や価値を高めるにはもってこい！？<br>エネルギッシュで魅力的な人になろう！！"
        }
      },
      {
        "name": "作詞・作曲",
        "status": {
          "sociability": 2,
          "collect": 2,
          "multiPlay": -2,
          "selfPolishing": 2,
          "art": 2,
          "sport": -2,
          "it": 1,
          "margin": 2,
          "costPerformance": 2,
          "text": "■センスが光る<br>音楽による感動を自分の手で作り上げよう<br>作詞・作曲にもテクニックが多数！？"
        }
      },
      {
        "name": "懸賞",
        "status": {
          "sociability": -2,
          "collect": 1,
          "multiPlay": -2,
          "selfPolishing": -2,
          "art": -2,
          "sport": -2,
          "it": 1,
          "margin": -1,
          "costPerformance": 2,
          "text": "■趣味で稼ぐ<br>趣味で少しづつ稼ごう<br>小物から海外旅行までなんでも手に入る！？"
        }
      },
      {
        "name": "ウクレレ",
        "status": {
          "sociability": 2,
          "collect": 1,
          "multiPlay": -2,
          "selfPolishing": 2,
          "art": 2,
          "sport": -2,
          "it": -2,
          "margin": 2,
          "costPerformance": -1,
          "text": "■センスが光る<br>安価で手軽で奥深い！<br>インテリアにもなる存在感が魅力！！"
        }
      },
      {
        "name": "コーヒー・紅茶",
        "status": {
          "sociability": 2,
          "collect": 2,
          "multiPlay": -2,
          "selfPolishing": 0,
          "art": 0,
          "sport": -2,
          "it": -2,
          "margin": 1,
          "costPerformance": -2,
          "text": "■大人の癒し<br>どの銘柄が好み？リラックス効果で疲れを癒そう<br>美味しく味わうだけでなく、「薬」としても重宝されていた！？"
        }
      },
      {
        "name": "お菓子作り",
        "status": {
          "sociability": 2,
          "collect": 2,
          "multiPlay": -2,
          "selfPolishing": 2,
          "art": 2,
          "sport": -2,
          "it": -2,
          "margin": 2,
          "costPerformance": -2,
          "text": "■美味しいものづくり<br>何と言っても香りがいい！<br>作って、見て、食べて楽しめる！色々なお菓子作りに挑戦しよう！！"
        }
      },
      {
        "name": "けん玉",
        "status": {
          "sociability": -2,
          "collect": -2,
          "multiPlay": -2,
          "selfPolishing": 1,
          "art": -2,
          "sport": -2,
          "it": -2,
          "margin": -2,
          "costPerformance": 1,
          "text": "■特技<br>脳にも良い効果がある！？<br>いつでもどこでもかっこいい技を決めよう！"
        }
      },
      {
        "name": "銀細工",
        "status": {
          "sociability": 1,
          "collect": 2,
          "multiPlay": -2,
          "selfPolishing": 2,
          "art": 2,
          "sport": -2,
          "it": -2,
          "margin": 1,
          "costPerformance": -2,
          "text": "■センスが光る<br>使い込めば使い込むほど味が出る！<br>硫化を引き取りながら独特の色を作り上げよう！！"
        }
      },
      {
        "name": "貨幣集め",
        "status": {
          "sociability": -2,
          "collect": 2,
          "multiPlay": -2,
          "selfPolishing": -2,
          "art": 1,
          "sport": -2,
          "it": -2,
          "margin": -2,
          "costPerformance": -2,
          "text": "■コレクション<br>歴史の裏付けを取集！？<br>資産として保持しておくと良いことがあるかも！？"
        }
      },
      {
        "name": "家庭菜園",
        "status": {
          "sociability": 2,
          "collect": 2,
          "multiPlay": -2,
          "selfPolishing": -2,
          "art": 2,
          "sport": -2,
          "it": -2,
          "margin": 1,
          "costPerformance": 1,
          "text": "■美味しいものづくり<br>食べるだけでなくインテリアとしてもオススメ！<br>百均で手軽に始められるのも魅力！！"
        }
      },
      {
        "name": "カルトナージュ",
        "status": {
          "sociability": 2,
          "collect": 2,
          "multiPlay": -2,
          "selfPolishing": 1,
          "art": 2,
          "sport": -2,
          "it": -2,
          "margin": 1,
          "costPerformance": -1,
          "text": "■オシャレなものづくり<br>厚紙細工で、身近な小物から椅子や家具の調度品までつくれる！？<br>手軽なのに作品の幅がとても広い！"
        }
      },
      {
        "name": "カリグラフィ",
        "status": {
          "sociability": 2,
          "collect": 1,
          "multiPlay": -2,
          "selfPolishing": 2,
          "art": 2,
          "sport": -2,
          "it": -2,
          "margin": -1,
          "costPerformance": 2,
          "text": "■自己研磨<br>日本人に向いている！？<br>文字で魅了しよう！！"
        }
      },
      {
        "name": "カメラ・写真",
        "status": {
          "sociability": 1,
          "collect": 2,
          "multiPlay": -2,
          "selfPolishing": 2,
          "art": 2,
          "sport": -2,
          "it": -2,
          "margin": 1,
          "costPerformance": -2,
          "text": "■コレクション<br>その一瞬を永遠の思い出に！<br>同じ被写体を撮っても全然違う写真に！？"
        }
      },
      {
        "name": "ゲーム",
        "status": {
          "sociability": -2,
          "collect": 0,
          "multiPlay": -1,
          "selfPolishing": -2,
          "art": 2,
          "sport": 1,
          "it": 1,
          "margin": 1,
          "costPerformance": -2,
          "text": "■インド派の鉄板<br>目的や目標を無限に追求できる！<br>仮想空間に浸って創造力を膨らまそう！！"
        }
      },
      {
        "name": "ネットオークション",
        "status": {
          "sociability": 1,
          "collect": 2,
          "multiPlay": -2,
          "selfPolishing": -2,
          "art": -2,
          "sport": -2,
          "it": 1,
          "margin": 1,
          "costPerformance": -1,
          "text": "■趣味で稼ぐ<br>あなたにとっては要らないものでも高く売れるかも！？<br>ネットで手軽に！ポイントでお得に！お買い物を楽しもう！！"
        }
      },
      {
        "name": "切手集め",
        "status": {
          "sociability": -2,
          "collect": 2,
          "multiPlay": -2,
          "selfPolishing": -2,
          "art": 1,
          "sport": -2,
          "it": -2,
          "margin": -2,
          "costPerformance": -2,
          "text": "■コレクション<br>小さい切手にはデザインが凝縮されている！？<br>経済情勢や切手収集のトレンドによっては価値が変化する投資性も！！"
        }
      },
      {
        "name": "投資・株・FX・BO",
        "status": {
          "sociability": 2,
          "collect": 2,
          "multiPlay": -2,
          "selfPolishing": 2,
          "art": -2,
          "sport": -2,
          "it": 2,
          "margin": 1,
          "costPerformance": 0,
          "text": "■資産運用<br>誰でも始められる稼ぎ手段<br>株主優待だけで暮らすのも難しくないかも！？"
        }
      },
      {
        "name": "料理",
        "status": {
          "sociability": 2,
          "collect": 1,
          "multiPlay": -2,
          "selfPolishing": 2,
          "art": 1,
          "sport": -2,
          "it": -2,
          "margin": 1,
          "costPerformance": 1,
          "text": "■美味しいものづくり<br>色々な変化を加えて、より美味しい料理を目指そう！<br>料理ができるとモテるかも！？"
        }
      },
      {
        "name": "アニメ鑑賞",
        "status": {
          "sociability": -1,
          "collect": 1,
          "multiPlay": -2,
          "selfPolishing": -2,
          "art": 1,
          "sport": -2,
          "it": 1,
          "margin": -2,
          "costPerformance": 2,
          "text": "■インドア派の鉄板<br>世界に誇れるコンテンツ！<br>アニメだからこそ楽しめる世界観に浸ろう！！"
        }
      },
      {
        "name": "鉄道",
        "status": {
          "sociability": -1,
          "collect": 2,
          "multiPlay": -2,
          "selfPolishing": -2,
          "art": 1,
          "sport": -2,
          "it": 1,
          "margin": -2,
          "costPerformance": -1,
          "text": "■意外性抜群<br>写真を撮るだけで絵になるそのデザイン性が魅力！<br>乗っても撮っても聞いても楽しめる！！"
        }
      },
      {
        "name": "アクアリウム",
        "status": {
          "sociability": -1,
          "collect": 2,
          "multiPlay": -2,
          "selfPolishing": -2,
          "art": 1,
          "sport": -2,
          "it": -2,
          "margin": 1,
          "costPerformance": -1,
          "text": "■オシャレな癒し<br>自分で創り上げる小さな海の世界！<br>美しいインテリアとしても大活躍！！"
        }
      },
      {
        "name": "Web制作・Webデザイン",
        "status": {
          "sociability": 2,
          "collect": -1,
          "multiPlay": -2,
          "selfPolishing": 2,
          "art": 2,
          "sport": -2,
          "it": 2,
          "margin": 2,
          "costPerformance": -1,
          "text": "■趣味で稼ぐ<br>PCだからこそ自由自在に表現できる<br>需要は高まる一方なので、フリーとして稼ぐことも！？"
        }
      },
      {
        "name": "資格取得",
        "status": {
          "sociability": 2,
          "collect": 1,
          "multiPlay": -2,
          "selfPolishing": 2,
          "art": 1,
          "sport": -2,
          "it": 1,
          "margin": 1,
          "costPerformance": 1,
          "text": "■自己研磨<br>将来性抜群！<br>自分にあった仕事に繋がることも！？"
        }
      },
      {
        "name": "Q&Aサイト",
        "status": {
          "sociability": 2,
          "collect": 1,
          "multiPlay": -2,
          "selfPolishing": 2,
          "art": -2,
          "sport": -2,
          "it": 2,
          "margin": -1,
          "costPerformance": 2,
          "text": "■自己研磨<br>自分の知識を活かして困っている人を助けよう！<br>人に感謝されながら自然と知識を増やしていこう！！"
        }
      },
      {
        "name": "読書",
        "status": {
          "sociability": -2,
          "collect": 1,
          "multiPlay": -2,
          "selfPolishing": 2,
          "art": -2,
          "sport": -2,
          "it": -2,
          "margin": 1,
          "costPerformance": 1,
          "text": "■インドア派の鉄板<br>いつでもどこでも楽しめて、想像力豊かに！<br>知識が広がるだけでなく、交流のきっかけにも！？"
        }
      },
      {
        "name": "ダーツ・ビリヤード",
        "status": {
          "sociability": 2,
          "collect": 1,
          "multiPlay": 1,
          "selfPolishing": -2,
          "art": -2,
          "sport": -2,
          "it": -2,
          "margin": 2,
          "costPerformance": -1,
          "text": "■手軽なスポーツ<br>単純で老若男女が楽しめる！<br>道具にこだわって見るのもいいかも！？"
        }
      },
      {
        "name": "instagram・twitter・facebook",
        "status": {
          "sociability": 2,
          "collect": 1,
          "multiPlay": -2,
          "selfPolishing": 2,
          "art": 1,
          "sport": -2,
          "it": 2,
          "margin": -2,
          "costPerformance": 2,
          "text": "■王道<br>同じ境遇の人と簡単に繋がれる！<br>小さな幸せを投稿していいねをもらおう！！"
        }
      },
      {
        "name": "バッティングセンター",
        "status": {
          "sociability": 1,
          "collect": -2,
          "multiPlay": -2,
          "selfPolishing": 1,
          "art": -2,
          "sport": 1,
          "it": -2,
          "margin": 2,
          "costPerformance": -1,
          "text": "■気分爽快<br>ストレス発散したいときはこれ！<br>女子人気も急上昇！デートに使える！？"
        }
      },
      {
        "name": "パラグライダー・パラセーリング・スカイダイビング",
        "status": {
          "sociability": 2,
          "collect": -2,
          "multiPlay": -2,
          "selfPolishing": 1,
          "art": -2,
          "sport": 2,
          "it": -2,
          "margin": 2,
          "costPerformance": -2,
          "text": "■気分爽快<br>空と海を全身で堪能しよう！<br>意外と都会でもできるかも！？"
        }
      },
      {
        "name": "バレーボール",
        "status": {
          "sociability": 2,
          "collect": -2,
          "multiPlay": 2,
          "selfPolishing": 1,
          "art": -2,
          "sport": 2,
          "it": -2,
          "margin": 2,
          "costPerformance": -1,
          "text": "■球技<br>球技の中で唯一、床にボールを落としてはいけないスポーツ！<br>ボールを繋げて心も繋がる！？"
        }
      },
      {
        "name": "ダンス・バレエ",
        "status": {
          "sociability": 2,
          "collect": -2,
          "multiPlay": 1,
          "selfPolishing": 1,
          "art": 1,
          "sport": 2,
          "it": -2,
          "margin": 2,
          "costPerformance": -2,
          "text": "■気分爽快<br>運動不足解消！ダイエット効果も！<br>リズム感が鍛えられ、音楽がもっと楽しくなる！？"
        }
      },
      {
        "name": "トライアスロン",
        "status": {
          "sociability": 2,
          "collect": -2,
          "multiPlay": -2,
          "selfPolishing": 2,
          "art": -2,
          "sport": 2,
          "it": -2,
          "margin": 2,
          "costPerformance": -2,
          "text": "■生涯スポーツ<br>トライアスロンの練習・大会を兼ねて観光！？<br>魅力的な身体と達成感を手に入れよう！！"
        }
      },
      {
        "name": "ハイキング・山登り・ボルダリング",
        "status": {
          "sociability": 2,
          "collect": -2,
          "multiPlay": -2,
          "selfPolishing": 2,
          "art": -2,
          "sport": 2,
          "it": -2,
          "margin": 2,
          "costPerformance": -2,
          "text": "■アウトドアの鉄板<br>自然の中を歩いて登って、全身で満喫しよう！<br>人の暖かさに触れることも！？"
        }
      },
      {
        "name": "テニス",
        "status": {
          "sociability": 2,
          "collect": -2,
          "multiPlay": 2,
          "selfPolishing": 1,
          "art": -2,
          "sport": 2,
          "it": -2,
          "margin": 2,
          "costPerformance": -2,
          "text": "■王道<br>ボールを叩き込む爽快感！<br>季節に関係なくいつでもできる！！"
        }
      },
      {
        "name": "ツーリング・サイクリング",
        "status": {
          "sociability": 2,
          "collect": -1,
          "multiPlay": -2,
          "selfPolishing": 1,
          "art": -2,
          "sport": 2,
          "it": -2,
          "margin": 2,
          "costPerformance": -2,
          "text": "■気分爽快<br>いつでも何処へでも出かけられる！<br>全身で風邪を感じながら遠出しよう！！"
        }
      },
      {
        "name": "乗馬",
        "status": {
          "sociability": 2,
          "collect": -2,
          "multiPlay": -2,
          "selfPolishing": 1,
          "art": 1,
          "sport": 2,
          "it": -2,
          "margin": 2,
          "costPerformance": -2,
          "text": "■意外性抜群<br>乗っているだけで運動不足解消！？<br>馬とのコミュニケーションで心も癒されよう！！"
        }
      },
      {
        "name": "水泳",
        "status": {
          "sociability": 1,
          "collect": -2,
          "multiPlay": -2,
          "selfPolishing": 1,
          "art": -2,
          "sport": 2,
          "it": -2,
          "margin": 2,
          "costPerformance": -1,
          "text": "■生涯スポーツ<br>水中で消費するカロリーは陸上の4倍！？<br>足腰の負担も少ないのにまんべんなく全身の筋肉を鍛えられる！"
        }
      },
      {
        "name": "射撃",
        "status": {
          "sociability": 2,
          "collect": 1,
          "multiPlay": -2,
          "selfPolishing": 1,
          "art": -2,
          "sport": 2,
          "it": -2,
          "margin": 2,
          "costPerformance": -2,
          "text": "■気分爽快<br>実銃を撃つという、誰にでも出来ることではない非日常性からくる満足感！<br>撃つ前の緊張感と撃ったあとの爽快感が魅力！！"
        }
      },
      {
        "name": "スキー",
        "status": {
          "sociability": 2,
          "collect": -2,
          "multiPlay": -2,
          "selfPolishing": 1,
          "art": -2,
          "sport": 2,
          "it": -2,
          "margin": 2,
          "costPerformance": -2,
          "text": "■非日常スポーツ<br>魅力は何と言ってもスピード感！<br>澄んだ空気、満点の星空、温泉、美味しいお酒と満喫要素はいっぱい！！"
        }
      },
      {
        "name": "サバイバルゲーム",
        "status": {
          "sociability": 2,
          "collect": 2,
          "multiPlay": 2,
          "selfPolishing": 1,
          "art": -2,
          "sport": 2,
          "it": -2,
          "margin": 2,
          "costPerformance": -2,
          "text": "■<br><br>"
        }
      },
      {
        "name": "マラソン・ジョギング・散歩",
        "status": {
          "sociability": 2,
          "collect": -2,
          "multiPlay": -2,
          "selfPolishing": 1,
          "art": -2,
          "sport": 1,
          "it": -2,
          "margin": 1,
          "costPerformance": 1,
          "text": "■<br><br>"
        }
      },
      {
        "name": "スノボー・スキー・スケボー",
        "status": {
          "sociability": 2,
          "collect": -2,
          "multiPlay": -2,
          "selfPolishing": 1,
          "art": -2,
          "sport": 2,
          "it": -2,
          "margin": 2,
          "costPerformance": -2,
          "text": "■<br><br>"
        }
      },
      {
        "name": "格闘技",
        "status": {
          "sociability": 2,
          "collect": -2,
          "multiPlay": -2,
          "selfPolishing": 1,
          "art": -2,
          "sport": 2,
          "it": -2,
          "margin": 2,
          "costPerformance": -1,
          "text": "■<br><br>"
        }
      },
      {
        "name": "ゴルフ",
        "status": {
          "sociability": 2,
          "collect": -2,
          "multiPlay": -2,
          "selfPolishing": 1,
          "art": -2,
          "sport": 2,
          "it": -2,
          "margin": 2,
          "costPerformance": -2,
          "text": "■<br><br>"
        }
      },
      {
        "name": "カラオケ",
        "status": {
          "sociability": 1,
          "collect": -2,
          "multiPlay": -1,
          "selfPolishing": 2,
          "art": 1,
          "sport": 2,
          "it": -2,
          "margin": -1,
          "costPerformance": -1,
          "text": "■<br><br>"
        }
      },
      {
        "name": "カヌー",
        "status": {
          "sociability": 1,
          "collect": -2,
          "multiPlay": -2,
          "selfPolishing": -1,
          "art": -2,
          "sport": 1,
          "it": -2,
          "margin": 2,
          "costPerformance": -1,
          "text": "■<br><br>"
        }
      },
      {
        "name": "エアロビクス",
        "status": {
          "sociability": 2,
          "collect": -2,
          "multiPlay": 0,
          "selfPolishing": 2,
          "art": -2,
          "sport": 2,
          "it": -2,
          "margin": 1,
          "costPerformance": -1,
          "text": "■<br><br>"
        }
      },
      {
        "name": "サーフィン",
        "status": {
          "sociability": 2,
          "collect": 1,
          "multiPlay": -1,
          "selfPolishing": 2,
          "art": -1,
          "sport": 2,
          "it": -2,
          "margin": 2,
          "costPerformance": -1,
          "text": "■<br><br>"
        }
      },
      {
        "name": "釣り",
        "status": {
          "sociability": 1,
          "collect": 1,
          "multiPlay": -2,
          "selfPolishing": 1,
          "art": -2,
          "sport": 1,
          "it": -2,
          "margin": 2,
          "costPerformance": -1,
          "text": "■<br><br>"
        }
      },
      {
        "name": "狩猟",
        "status": {
          "sociability": 1,
          "collect": 2,
          "multiPlay": -1,
          "selfPolishing": 1,
          "art": -2,
          "sport": 1,
          "it": -2,
          "margin": 2,
          "costPerformance": -2,
          "text": "■<br><br>"
        }
      },
      {
        "name": "ボーリング",
        "status": {
          "sociability": 1,
          "collect": -2,
          "multiPlay": -1,
          "selfPolishing": -2,
          "art": -2,
          "sport": 1,
          "it": -2,
          "margin": 1,
          "costPerformance": -1,
          "text": "■<br><br>"
        }
      },
      {
        "name": "体操・ヨガ",
        "status": {
          "sociability": 1,
          "collect": -2,
          "multiPlay": -2,
          "selfPolishing": 1,
          "art": -1,
          "sport": 2,
          "it": -2,
          "margin": 1,
          "costPerformance": 0,
          "text": "■<br><br>"
        }
      },
      {
        "name": "神社巡り・御朱印集め",
        "status": {
          "sociability": 1,
          "collect": 2,
          "multiPlay": -2,
          "selfPolishing": -1,
          "art": -2,
          "sport": -1,
          "it": -2,
          "margin": 1,
          "costPerformance": 2,
          "text": "■<br><br>"
        }
      },
      {
        "name": "ヒッチハイク",
        "status": {
          "sociability": 2,
          "collect": -2,
          "multiPlay": -2,
          "selfPolishing": 2,
          "art": -2,
          "sport": -2,
          "it": -2,
          "margin": 2,
          "costPerformance": 1,
          "text": "■<br><br>"
        }
      },
      {
        "name": "ソープカービング",
        "status": {
          "sociability": 1,
          "collect": 1,
          "multiPlay": -2,
          "selfPolishing": 2,
          "art": 2,
          "sport": 2,
          "it": -2,
          "margin": 1,
          "costPerformance": -1,
          "text": "■<br><br>"
        }
      },
      {
        "name": "ジグソーパズル",
        "status": {
          "sociability": -2,
          "collect": -1,
          "multiPlay": -2,
          "selfPolishing": 1,
          "art": 1,
          "sport": -2,
          "it": -2,
          "margin": 1,
          "costPerformance": -1,
          "text": "■<br><br>"
        }
      },
      {
        "name": "旅行",
        "status": {
          "sociability": 2,
          "collect": -2,
          "multiPlay": 0,
          "selfPolishing": 2,
          "art": 0,
          "sport": 1,
          "it": -2,
          "margin": 2,
          "costPerformance": -2,
          "text": "■<br><br>"
        }
      },
      {
        "name": "キャンプ",
        "status": {
          "sociability": 2,
          "collect": -2,
          "multiPlay": 0,
          "selfPolishing": 1,
          "art": -2,
          "sport": 2,
          "it": -2,
          "margin": 2,
          "costPerformance": -2,
          "text": "■<br><br>"
        }
      },
      {
        "name": "温泉巡り",
        "status": {
          "sociability": 2,
          "collect": 1,
          "multiPlay": -1,
          "selfPolishing": 1,
          "art": -2,
          "sport": -1,
          "it": -2,
          "margin": 2,
          "costPerformance": -2,
          "text": "■<br><br>"
        }
      }
    ]
  }
}
